D_FlipFlop.v
// D_FlipFlop.v
module D_FlipFlop (
    input clk,
    input reset,
    input D,
    output reg Q
);

    always @(posedge clk or posedge reset) begin
        if (reset) begin
            Q <= 1'b0;
        end else begin
            Q <= D;
        end
    end

endmodule

Mux_8_to_1.v
// Mux_8_to_1.v
module Mux_8_to_1 (
    input [7:0] in,
    input [2:0] sel,
    output reg out
);

    always @(*) begin
        case (sel)
            3'b000: out = in[0];
            3'b001: out = in[1];
            3'b010: out = in[2];
            3'b011: out = in[3];
            3'b100: out = in[4];
            3'b101: out = in[5];
            3'b110: out = in[6];
            3'b111: out = in[7];
            default: out = 1'bx;
        endcase
    end

endmodule

Universal_Shift_Register.v
// Universal_Shift_Register.v
module Universal_Shift_Register (
    input clk,
    input reset,
    input [2:0] mode,
    input data_in,
    input parallel_in_0,
    input parallel_in_1,
    input parallel_in_2,
    input parallel_in_3,
    output reg [3:0] Q
);

    wire mux_out;
    wire Q0, Q1, Q2, Q3; // Intermediate wires

    Mux_8_to_1 mux (
        .in ({parallel_in_3, parallel_in_2, parallel_in_1, parallel_in_0, data_in, Q[3], Q[0], 1'b0}),
        .sel(mode),
        .out(mux_out)
    );

    D_FlipFlop ff0 (
        .clk(clk),
        .reset(reset),
        .D(mux_out),
        .Q(Q0) // Connect to wire Q0
    );

    D_FlipFlop ff1 (
        .clk(clk),
        .reset(reset),
        .D(Q0), // Connect wire Q0
        .Q(Q1) // Connect to wire Q1
    );

    D_FlipFlop ff2 (
        .clk(clk),
        .reset(reset),
        .D(Q1), // Connect wire Q1
        .Q(Q2) // Connect to wire Q2
    );

    D_FlipFlop ff3 (
        .clk(clk),
        .reset(reset),
        .D(Q2), // Connect wire Q2
        .Q(Q3) // Connect to wire Q3
    );

    always @(*) begin // Assign the wires to the output reg
        Q[0] = Q0;
        Q[1] = Q1;
        Q[2] = Q2;
        Q[3] = Q3;
    end

endmodule

Universal_Shift_Register_tb.v
`timescale 1ns / 1ps

module Universal_Shift_Register_tb;

    reg clk;
    reg reset;
    reg [2:0] mode;
    reg data_in;
    reg parallel_in_0;
    reg parallel_in_1;
    reg parallel_in_2;
    reg parallel_in_3;
    wire [3:0] Q;

    Universal_Shift_Register uut (
        .clk(clk),
        .reset(reset),
        .mode(mode),
        .data_in(data_in),
        .parallel_in_0(parallel_in_0),
        .parallel_in_1(parallel_in_1),
        .parallel_in_2(parallel_in_2),
        .parallel_in_3(parallel_in_3),
        .Q(Q)
    );

    initial begin
        $dumpfile("dump.vcd"); // Add this line
        $dumpvars(0, Universal_Shift_Register_tb); // Add this line

        clk = 0;
        reset = 1;
        mode = 3'b000;
        data_in = 1'b0;
        parallel_in_0 = 1'b0;
        parallel_in_1 = 1'b0;
        parallel_in_2 = 1'b0;
        parallel_in_3 = 1'b0;

        #10;
        reset = 0;
        #10;

        mode = 3'b000;
        #20;

        mode = 3'b001;
        data_in = 1'b1;
        #10;
        data_in = 1'b0;
        #10;
        data_in = 1'b1;
        #10;

        mode = 3'b100;
        data_in = 1'b1;
        #10;
        data_in = 1'b0;
        #10;
        data_in = 1'b1;
        #10;

        mode = 3'b010;
        parallel_in_0 = 1'b1;
        parallel_in_1 = 1'b0;
        parallel_in_2 = 1'b1;
        parallel_in_3 = 1'b0;
        #20;

        mode = 3'b011;
        #30;

        $finish;
    end

    always #5 clk = ~clk;

    initial begin
        $monitor("Time=%0t, reset=%b, mode=%b, data_in=%b, parallel_in=%b%b%b%b, Q=%b",
                 $time, reset, mode, data_in, parallel_in_3, parallel_in_2, parallel_in_1, parallel_in_0, Q);
    end

endmodule

dump.vcd
$date
	Sun Mar 09 09:08:33 2025
$end
$version
	Icarus Verilog
$end
$timescale
	1ps
$end
$scope module Universal_Shift_Register_tb $end
$var wire 4 ! Q [3:0] $end
$var reg 1 " clk $end
$var reg 1 # data_in $end
$var reg 3 $ mode [2:0] $end
$var reg 1 % parallel_in_0 $end
$var reg 1 & parallel_in_1 $end
$var reg 1 ' parallel_in_2 $end
$var reg 1 ( parallel_in_3 $end
$var reg 1 ) reset $end
$scope module uut $end
$var wire 1 " clk $end
$var wire 1 # data_in $end
$var wire 3 * mode [2:0] $end
$var wire 1 % parallel_in_0 $end
$var wire 1 & parallel_in_1 $end
$var wire 1 ' parallel_in_2 $end
$var wire 1 ( parallel_in_3 $end
$var wire 1 ) reset $end
$var wire 1 + mux_out $end
$var wire 1 , Q3 $end
$var wire 1 - Q2 $end
$var wire 1 . Q1 $end
$var wire 1 / Q0 $end
$var reg 4 0 Q [3:0] $end
$scope module ff0 $end
$var wire 1 " clk $end
$var wire 1 ) reset $end
$var wire 1 + D $end
$var reg 1 / Q $end
$upscope $end
$scope module ff1 $end
$var wire 1 / D $end
$var wire 1 " clk $end
$var wire 1 ) reset $end
$var reg 1 . Q $end
$upscope $end
$scope module ff2 $end
$var wire 1 . D $end
$var wire 1 " clk $end
$var wire 1 ) reset $end
$var reg 1 - Q $end
$upscope $end
$scope module ff3 $end
$var wire 1 - D $end
$var wire 1 " clk $end
$var wire 1 ) reset $end
$var reg 1 , Q $end
$upscope $end
$scope module mux $end
$var wire 8 1 in [7:0] $end
$var wire 3 2 sel [2:0] $end
$var reg 1 + out $end
$upscope $end
$upscope $end
$upscope $end
$enddefinitions $end
$comment Show the parameter values. $end
$dumpall
$end
#0
$dumpvars
b0 2
b0 1
b0 0
0/
0.
0-
0,
0+
b0 *
1)
0(
0'
0&
0%
b0 $
0#
0"
b0 !
$end
#5000
1"
#10000
0"
0)
#15000
1"
#20000
0"
#25000
1"
#30000
0"
#35000
1"
#40000
0"
b1000 1
1#
b1 $
b1 *
b1 2
#45000
1"
#50000
0"
b0 1
0#
#55000
1"
#60000
0"
b1000 1
1#
#65000
1"
#70000
0"
b100 $
b100 *
b100 2
#75000
1"
#80000
0"
b0 1
0#
#85000
1"
#90000
0"
b1000 1
1#
#95000
1"
#100000
0"
1'
b1011000 1
1%
b10 $
b10 *
b10 2
#105000
1"
#110000
0"
#115000
1"
#120000
1+
0"
b11 $
b11 *
b11 2
#125000
b1011010 1
b1 !
b1 0
1/
1"
#130000
0"
#135000
b11 !
b11 0
1.
1"
#140000
0"
#145000
b111 !
b111 0
1-
1"
